plex_version
